lark_dynamic/__init__.py
lark_dynamic/atoms.py
lark_dynamic/combinators.py
lark_dynamic/constants.py
lark_dynamic/definitions.py
lark_dynamic/grammar.py
lark_dynamic/modifier.py
lark_dynamic/py.typed
lark_dynamic/token.py
lark_dynamic/utils.py
lark_dynamic/variable.py
lark_dynamic-1.1.4.dist-info/LICENSE
lark_dynamic-1.1.4.dist-info/METADATA
lark_dynamic-1.1.4.dist-info/WHEEL
lark_dynamic-1.1.4.dist-info/RECORD
