Metadata-Version: 2.1
Name: lark-dynamic
Version: 1.1.4
Summary: Grammar generator for Lark parsing toolkit
License: MIT
Author: Dmitry Gritsenko
Author-email: k01419q45@ya.ru
Requires-Python: >=3.7,<4.0
Classifier: License :: OSI Approved :: MIT License
Classifier: Programming Language :: Python :: 3
Classifier: Programming Language :: Python :: 3.7
Classifier: Programming Language :: Python :: 3.8
Classifier: Programming Language :: Python :: 3.9
Classifier: Programming Language :: Python :: 3.10
Classifier: Programming Language :: Python :: 3.11
